Products.Marshall-2.4.1-py2.7-nspkg.pth
Products/Marshall/__init__.py
Products/Marshall/config.py
Products/Marshall/configure.zcml
Products/Marshall/exceptions.py
Products/Marshall/export.py
Products/Marshall/expression.py
Products/Marshall/makefile.in
Products/Marshall/marshaller.py
Products/Marshall/profile.py
Products/Marshall/registry.py
Products/Marshall/utils.py
Products/Marshall/Extensions/__init__.py
Products/Marshall/Extensions/export.py
Products/Marshall/doc/ATETREE.txt
Products/Marshall/doc/README.txt
Products/Marshall/handlers/__init__.py
Products/Marshall/handlers/atxml.py
Products/Marshall/handlers/base.py
Products/Marshall/handlers/primaryfield.py
Products/Marshall/handlers/rfc822header.py
Products/Marshall/interfaces/__init__.py
Products/Marshall/interfaces/predicate.py
Products/Marshall/namespaces/__init__.py
Products/Marshall/namespaces/adobens.py
Products/Marshall/namespaces/atns.py
Products/Marshall/namespaces/cmfns.py
Products/Marshall/namespaces/dcns.py
Products/Marshall/namespaces/uuns.py
Products/Marshall/predicates/__init__.py
Products/Marshall/predicates/_base.py
Products/Marshall/predicates/_xmlns.py
Products/Marshall/profiles/default/metadata.xml
Products/Marshall/profiles/uninstall/metadata.xml
Products/Marshall/tests/__init__.py
Products/Marshall/tests/base.py
Products/Marshall/tests/test_export.py
Products/Marshall/tests/test_marshall.py
Products/Marshall/tests/test_predicate.py
Products/Marshall/tests/data/file.html
Products/Marshall/tests/data/file.pdf
Products/Marshall/tests/data/file.txt
Products/Marshall/tests/data/image.gif
Products/Marshall/tests/examples/__init__.py
Products/Marshall/tests/examples/blob.py
Products/Marshall/tests/examples/person.py
Products/Marshall/tests/export/atxml/test
Products/Marshall/tests/export/atxml/.metadata/test
Products/Marshall/tests/input/atxml/Document.xml
Products/Marshall/tests/input/primary_field/Document.txt
Products/Marshall/tests/input/rfc822/Document.txt
Products.Marshall-2.4.1.dist-info/METADATA
Products.Marshall-2.4.1.dist-info/WHEEL
Products.Marshall-2.4.1.dist-info/namespace_packages.txt
Products.Marshall-2.4.1.dist-info/top_level.txt
Products.Marshall-2.4.1.dist-info/RECORD
