Metadata-Version: 2.1
Name: Products.Marshall
Version: 2.4.1
Summary: Configurable Marshallers for Archetypes
Home-page: https://pypi.org/project/Products.Marshall
Author: Sidnei da Silve and others
Author-email: plone-developers@lists.sourceforge.net
License: GPL
Keywords: web zope application server webdav ftp
Platform: UNKNOWN
Classifier: Development Status :: 5 - Production/Stable
Classifier: Environment :: Web Environment
Classifier: Framework :: Zope2
Classifier: Framework :: Zope :: 4
Classifier: Framework :: Plone
Classifier: Framework :: Plone :: 5.2
Classifier: License :: OSI Approved :: GNU General Public License (GPL)
Classifier: Operating System :: OS Independent
Classifier: Programming Language :: Python
Classifier: Programming Language :: Python :: 2.7
Classifier: Topic :: Internet :: WWW/HTTP
Classifier: Topic :: Internet :: File Transfer Protocol (FTP)
Requires-Dist: setuptools
Requires-Dist: six
Requires-Dist: transaction
Requires-Dist: plone.uuid
Requires-Dist: zope.contenttype
Requires-Dist: zope.deprecation
Requires-Dist: zope.interface
Requires-Dist: Products.Archetypes
Requires-Dist: Products.CMFCore
Requires-Dist: Products.GenericSetup
Requires-Dist: Acquisition
Requires-Dist: DateTime
Requires-Dist: ExtensionClass
Requires-Dist: Zope2
Provides-Extra: test
Requires-Dist: Products.ATContentTypes ; extra == 'test'
